devbot_sa/__init__.py
devbot_sa/devbot.py
devbot_sa/devbot_assistant.py
devbot_sa/gui.py
devbot_sa/pdfGenerator.py
devbot_sa/prompts.py
genai4sa-0.2.1.dist-info/LICENSE
genai4sa-0.2.1.dist-info/METADATA
genai4sa-0.2.1.dist-info/WHEEL
genai4sa-0.2.1.dist-info/entry_points.txt
genai4sa-0.2.1.dist-info/top_level.txt
genai4sa-0.2.1.dist-info/RECORD
