Metadata-Version: 2.1
Name: genai4sa
Version: 0.2.1
Summary: A software architecture generation tool using LLMs
Author-email: Hashim Khan <hashimahmedkhan2002@gmail.com>
Requires-Python: >=3.8
License-File: LICENSE
Requires-Dist: langchain
Requires-Dist: langchain-core
Requires-Dist: langchain-openai
Requires-Dist: langchain-google-genai
Requires-Dist: langchain-groq
Requires-Dist: nbconvert
Requires-Dist: python-dotenv==1.0.0
Requires-Dist: uvicorn==0.25.0
Requires-Dist: customtkinter==5.2.2
Requires-Dist: plantuml
Requires-Dist: reportlab==4.4.0
Requires-Dist: networkx
Requires-Dist: numpy
Requires-Dist: scipy
